link/__init__.py
link/client.py
wattzon_link-0.1.dev5.dist-info/DESCRIPTION.rst
wattzon_link-0.1.dev5.dist-info/METADATA
wattzon_link-0.1.dev5.dist-info/RECORD
wattzon_link-0.1.dev5.dist-info/WHEEL
wattzon_link-0.1.dev5.dist-info/metadata.json
wattzon_link-0.1.dev5.dist-info/top_level.txt
