Metadata-Version: 2.0
Name: wattzon-link
Version: 0.1.dev5
Summary: WattzOn Link API client
Home-page: https://github.com/WattzOn/link-python-client
Author: UNKNOWN
Author-email: UNKNOWN
License: UNKNOWN
Keywords: wattzon link
Platform: UNKNOWN
Classifier: Development Status :: 3 - Alpha
Classifier: Intended Audience :: Developers
Classifier: Programming Language :: Python :: 3
Requires-Python: >=3
Requires-Dist: requests
